jdn_text_writer/__init__.py
jdn_text_writer/server.py
jdn_text_writer-0.1.0.dist-info/METADATA
jdn_text_writer-0.1.0.dist-info/WHEEL
jdn_text_writer-0.1.0.dist-info/entry_points.txt
jdn_text_writer-0.1.0.dist-info/RECORD
